quickperms/__init__.py
quickperms/quickperms.py
quickperms-0.1.1.dist-info/WHEEL
quickperms-0.1.1.dist-info/METADATA
quickperms-0.1.1.dist-info/RECORD
